lsq_analyzer/__init__.py
lsq_analyzer/lsq_analyzer/__init__.py
lsq_analyzer/lsq_analyzer/lsq_library.py
LSQ_Analyzer-1.1.dist-info/METADATA
LSQ_Analyzer-1.1.dist-info/WHEEL
LSQ_Analyzer-1.1.dist-info/top_level.txt
LSQ_Analyzer-1.1.dist-info/RECORD
