Metadata-Version: 2.1
Name: LSQ-Analyzer
Version: 1.1
Summary: Библиотека для анализа спектров МНК с неотрицательными коэффициентами
Home-page: UNKNOWN
License: UNKNOWN
Platform: UNKNOWN
Requires-Dist: numpy
Requires-Dist: scipy
Requires-Dist: matplotlib
